{
  "id": 297,
  "name": "Fern1",
  "description": "Fern1 is a solid block representing a small, decorative fern plant, likely used for adding visual detail and natural elements to environments. Its opaque nature means it will block light and movement.",
  "modifiers": {
    "0": {
      "visibility": {
        "shape": 1,
        "textures": {
          "0": "textures/block/basic/fern1.png"
        }
      },
      "physics": {
        "solid": true
      }
    }
  },
  "description_old": "Fern1 block"
}
