{
  "id": 338,
  "name": "Grindstone Round",
  "description": "The Grindstone Round is a solid, stone-like block used for building and decorative purposes, visually representing a section of a grindstone. Its solid nature makes it ideal for constructing structures and landscapes.",
  "modifiers": {
    "0": {
      "visibility": {
        "shape": 1,
        "textures": {
          "0": "textures/block/basic/grindstone_round.png"
        }
      },
      "physics": {
        "solid": true
      }
    }
  },
  "description_old": "Grindstone Round - Building material"
}
