{
  "id": 199,
  "name": "Cartography Table Side3",
  "description": "This block represents a solid, wood-textured side panel of a cartography table. It is likely used for constructing or detailing cartography table structures within the game world.",
  "modifiers": {
    "0": {
      "visibility": {
        "shape": 1,
        "textures": {
          "0": "textures/block/basic/cartography_table_side3.png"
        }
      },
      "physics": {
        "solid": true
      }
    }
  },
  "description_old": "Cartography Table Side3 block"
}
